{"verses":{"1":[{"p":1,"ar":"إِنَّآ","pos":"P","morphemes":[{"ar":"إِنَّ","pos":"P"},{"ar":"آ","pos":"PRON","suffix":true}],"f":{"cas":"ACC"},"lemma":"إِنّ"},{"p":2,"ar":"أَعْطَيْنَٰكَ","pos":"V","morphemes":[{"ar":"أَعْطَيْ","pos":"V"},{"ar":"نَٰ","pos":"PRON","suffix":true},{"ar":"كَ","pos":"PRON","suffix":true}],"f":{"per":1,"num":"P","form":4,"asp":"PERF"},"root":"عطو","lemma":"أَعْطَى"},{"p":3,"ar":"ٱلْكَوْثَرَ","pos":"N","morphemes":[{"ar":"ٱلْ","pos":"DET","prefix":true},{"ar":"كَوْثَرَ","pos":"N"}],"f":{"gen":"M","cas":"ACC"},"root":"كثر","lemma":"كَوْثَر"}],"2":[{"p":1,"ar":"فَصَلِّ","pos":"V","morphemes":[{"ar":"فَ","pos":"REM","prefix":true},{"ar":"صَلِّ","pos":"V"}],"f":{"per":2,"gen":"M","num":"S","form":2,"asp":"IMPV"},"root":"صلو","lemma":"صَلَّى"},{"p":2,"ar":"لِرَبِّكَ","pos":"N","morphemes":[{"ar":"لِ","pos":"P","prefix":true},{"ar":"رَبِّ","pos":"N"},{"ar":"كَ","pos":"PRON","suffix":true}],"f":{"gen":"M","cas":"GEN"},"root":"ربب","lemma":"رَبّ"},{"p":3,"ar":"وَٱنْحَرْ","pos":"V","morphemes":[{"ar":"وَ","pos":"CONJ","prefix":true},{"ar":"ٱنْحَرْ","pos":"V"}],"f":{"per":2,"gen":"M","num":"S","form":1,"asp":"IMPV"},"root":"نحر","lemma":"انْحَرْ"}],"3":[{"p":1,"ar":"إِنَّ","pos":"P","morphemes":[{"ar":"إِنَّ","pos":"P"}],"f":{"cas":"ACC"},"lemma":"إِنّ"},{"p":2,"ar":"شَانِئَكَ","pos":"N","morphemes":[{"ar":"شَانِئَ","pos":"N"},{"ar":"كَ","pos":"PRON","suffix":true}],"f":{"gen":"M","cas":"ACC","form":1,"der":"AP"},"root":"شنأ","lemma":"شانِئ"},{"p":3,"ar":"هُوَ","pos":"PRON","morphemes":[{"ar":"هُوَ","pos":"PRON"}],"f":{"per":3,"gen":"M","num":"S"}},{"p":4,"ar":"ٱلْأَبْتَرُ","pos":"N","morphemes":[{"ar":"ٱلْ","pos":"DET","prefix":true},{"ar":"أَبْتَرُ","pos":"N"}],"f":{"gen":"M","cas":"NOM"},"root":"بتر","lemma":"أَبْتَر"}]}}