{"verses":{"1":[{"p":1,"ar":"إِذَا","pos":"T","morphemes":[{"ar":"إِذَا","pos":"T"}],"f":{},"lemma":"إِذا"},{"p":2,"ar":"ٱلسَّمَآءُ","pos":"N","morphemes":[{"ar":"ٱل","pos":"DET","prefix":true},{"ar":"سَّمَآءُ","pos":"N"}],"f":{"gen":"F","cas":"NOM"},"root":"سمو","lemma":"سَماء"},{"p":3,"ar":"ٱنشَقَّتْ","pos":"V","morphemes":[{"ar":"ٱنشَقَّتْ","pos":"V"}],"f":{"per":3,"gen":"F","num":"S","form":7,"asp":"PERF"},"root":"شقق","lemma":"انشَقَّ"}],"2":[{"p":1,"ar":"وَأَذِنَتْ","pos":"V","morphemes":[{"ar":"وَ","pos":"CONJ","prefix":true},{"ar":"أَذِنَتْ","pos":"V"}],"f":{"per":3,"gen":"F","num":"S","form":1,"asp":"PERF"},"root":"أذن","lemma":"أَذِنَ"},{"p":2,"ar":"لِرَبِّهَا","pos":"N","morphemes":[{"ar":"لِ","pos":"P","prefix":true},{"ar":"رَبِّ","pos":"N"},{"ar":"هَا","pos":"PRON","suffix":true}],"f":{"gen":"M","cas":"GEN"},"root":"ربب","lemma":"رَبّ"},{"p":3,"ar":"وَحُقَّتْ","pos":"V","morphemes":[{"ar":"وَ","pos":"CONJ","prefix":true},{"ar":"حُقَّتْ","pos":"V"}],"f":{"per":3,"gen":"F","num":"S","voice":"PASS","form":1,"asp":"PERF"},"root":"حقق","lemma":"حَقَّ"}],"3":[{"p":1,"ar":"وَإِذَا","pos":"T","morphemes":[{"ar":"وَ","pos":"CONJ","prefix":true},{"ar":"إِذَا","pos":"T"}],"f":{},"lemma":"إِذا"},{"p":2,"ar":"ٱلْأَرْضُ","pos":"N","morphemes":[{"ar":"ٱلْ","pos":"DET","prefix":true},{"ar":"أَرْضُ","pos":"N"}],"f":{"gen":"F","cas":"NOM"},"root":"أرض","lemma":"أَرْض"},{"p":3,"ar":"مُدَّتْ","pos":"V","morphemes":[{"ar":"مُدَّتْ","pos":"V"}],"f":{"per":3,"gen":"F","num":"S","voice":"PASS","form":1,"asp":"PERF"},"root":"مدد","lemma":"مَدَّ"}],"4":[{"p":1,"ar":"وَأَلْقَتْ","pos":"V","morphemes":[{"ar":"وَ","pos":"CONJ","prefix":true},{"ar":"أَلْقَتْ","pos":"V"}],"f":{"per":3,"gen":"F","num":"S","form":4,"asp":"PERF"},"root":"لقي","lemma":"أَلْقَى"},{"p":2,"ar":"مَا","pos":"REL","morphemes":[{"ar":"مَا","pos":"REL"}],"f":{},"lemma":"ما"},{"p":3,"ar":"فِيهَا","pos":"P","morphemes":[{"ar":"فِي","pos":"P"},{"ar":"هَا","pos":"PRON","suffix":true}],"f":{},"lemma":"فِي"},{"p":4,"ar":"وَتَخَلَّتْ","pos":"V","morphemes":[{"ar":"وَ","pos":"CONJ","prefix":true},{"ar":"تَخَلَّتْ","pos":"V"}],"f":{"per":3,"gen":"F","num":"S","form":5,"asp":"PERF"},"root":"خلو","lemma":"تَخَلَّتْ"}],"5":[{"p":1,"ar":"وَأَذِنَتْ","pos":"V","morphemes":[{"ar":"وَ","pos":"CONJ","prefix":true},{"ar":"أَذِنَتْ","pos":"V"}],"f":{"per":3,"gen":"F","num":"S","form":1,"asp":"PERF"},"root":"أذن","lemma":"أَذِنَ"},{"p":2,"ar":"لِرَبِّهَا","pos":"N","morphemes":[{"ar":"لِ","pos":"P","prefix":true},{"ar":"رَبِّ","pos":"N"},{"ar":"هَا","pos":"PRON","suffix":true}],"f":{"gen":"M","cas":"GEN"},"root":"ربب","lemma":"رَبّ"},{"p":3,"ar":"وَحُقَّتْ","pos":"V","morphemes":[{"ar":"وَ","pos":"CONJ","prefix":true},{"ar":"حُقَّتْ","pos":"V"}],"f":{"per":3,"gen":"F","num":"S","voice":"PASS","form":1,"asp":"PERF"},"root":"حقق","lemma":"حَقَّ"}],"6":[{"p":1,"ar":"يَٰٓأَيُّهَا","pos":"N","morphemes":[{"ar":"يَٰٓ","pos":"VOC","prefix":true},{"ar":"أَيُّ","pos":"N"},{"ar":"هَا","pos":"P","suffix":true}],"f":{"cas":"ACC"},"root":"أيي","lemma":"أَيّ"},{"p":2,"ar":"ٱلْإِنسَٰنُ","pos":"N","morphemes":[{"ar":"ٱلْ","pos":"DET","prefix":true},{"ar":"إِنسَٰنُ","pos":"N"}],"f":{"gen":"M","cas":"NOM"},"root":"أنس","lemma":"إِنسان"},{"p":3,"ar":"إِنَّكَ","pos":"P","morphemes":[{"ar":"إِنَّ","pos":"P"},{"ar":"كَ","pos":"PRON","suffix":true}],"f":{"cas":"ACC"},"lemma":"إِنّ"},{"p":4,"ar":"كَادِحٌ","pos":"N","morphemes":[{"ar":"كَادِحٌ","pos":"N"}],"f":{"gen":"M","cas":"NOM","state":"INDEF","form":1,"der":"AP"},"root":"كدح","lemma":"كادِح"},{"p":5,"ar":"إِلَىٰ","pos":"P","morphemes":[{"ar":"إِلَىٰ","pos":"P"}],"f":{},"lemma":"إِلَى"},{"p":6,"ar":"رَبِّكَ","pos":"N","morphemes":[{"ar":"رَبِّ","pos":"N"},{"ar":"كَ","pos":"PRON","suffix":true}],"f":{"gen":"M","cas":"GEN"},"root":"ربب","lemma":"رَبّ"},{"p":7,"ar":"كَدْحًا","pos":"N","morphemes":[{"ar":"كَدْحًا","pos":"N"}],"f":{"gen":"M","cas":"ACC","state":"INDEF"},"root":"كدح","lemma":"كَدْح"},{"p":8,"ar":"فَمُلَٰقِيهِ","pos":"N","morphemes":[{"ar":"فَ","pos":"CONJ","prefix":true},{"ar":"مُلَٰقِي","pos":"N"},{"ar":"هِ","pos":"PRON","suffix":true}],"f":{"gen":"M","cas":"NOM","form":3,"der":"AP"},"root":"لقي","lemma":"مُلاقِي"}],"7":[{"p":1,"ar":"فَأَمَّا","pos":"P","morphemes":[{"ar":"فَ","pos":"REM","prefix":true},{"ar":"أَمَّا","pos":"P"}],"f":{},"lemma":"أَمّا"},{"p":2,"ar":"مَنْ","pos":"COND","morphemes":[{"ar":"مَنْ","pos":"COND"}],"f":{},"lemma":"مَن"},{"p":3,"ar":"أُوتِىَ","pos":"V","morphemes":[{"ar":"أُوتِىَ","pos":"V"}],"f":{"per":3,"gen":"M","num":"S","voice":"PASS","form":4,"asp":"PERF"},"root":"أتي","lemma":"آتَى"},{"p":4,"ar":"كِتَٰبَهُۥ","pos":"N","morphemes":[{"ar":"كِتَٰبَ","pos":"N"},{"ar":"هُۥ","pos":"PRON","suffix":true}],"f":{"gen":"M","cas":"ACC"},"root":"كتب","lemma":"كِتاب"},{"p":5,"ar":"بِيَمِينِهِۦ","pos":"N","morphemes":[{"ar":"بِ","pos":"P","prefix":true},{"ar":"يَمِينِ","pos":"N"},{"ar":"هِۦ","pos":"PRON","suffix":true}],"f":{"gen":"M","cas":"GEN"},"root":"يمن","lemma":"يَمِين"}],"8":[{"p":1,"ar":"فَسَوْفَ","pos":"FUT","morphemes":[{"ar":"فَ","pos":"RSLT","prefix":true},{"ar":"سَوْفَ","pos":"FUT"}],"f":{},"lemma":"سَوْف"},{"p":2,"ar":"يُحَاسَبُ","pos":"V","morphemes":[{"ar":"يُحَاسَبُ","pos":"V"}],"f":{"per":3,"gen":"M","num":"S","mood":"IND","voice":"PASS","form":3,"asp":"IMPF"},"root":"حسب","lemma":"حاسَبْ"},{"p":3,"ar":"حِسَابًا","pos":"N","morphemes":[{"ar":"حِسَابًا","pos":"N"}],"f":{"gen":"M","cas":"ACC","state":"INDEF","form":3,"der":"VN"},"root":"حسب","lemma":"حِساب"},{"p":4,"ar":"يَسِيرًا","pos":"ADJ","morphemes":[{"ar":"يَسِيرًا","pos":"ADJ"}],"f":{"gen":"M","num":"S","cas":"ACC","state":"INDEF"},"root":"يسر","lemma":"يَسِير"}],"9":[{"p":1,"ar":"وَيَنقَلِبُ","pos":"V","morphemes":[{"ar":"وَ","pos":"CONJ","prefix":true},{"ar":"يَنقَلِبُ","pos":"V"}],"f":{"per":3,"gen":"M","num":"S","mood":"IND","form":7,"asp":"IMPF"},"root":"قلب","lemma":"انقَلَبَ"},{"p":2,"ar":"إِلَىٰٓ","pos":"P","morphemes":[{"ar":"إِلَىٰٓ","pos":"P"}],"f":{},"lemma":"إِلَى"},{"p":3,"ar":"أَهْلِهِۦ","pos":"N","morphemes":[{"ar":"أَهْلِ","pos":"N"},{"ar":"هِۦ","pos":"PRON","suffix":true}],"f":{"gen":"M","cas":"GEN"},"root":"أهل","lemma":"أَهْل"},{"p":4,"ar":"مَسْرُورًا","pos":"N","morphemes":[{"ar":"مَسْرُورًا","pos":"N"}],"f":{"gen":"M","cas":"ACC","state":"INDEF","form":1,"der":"PP"},"root":"سرر","lemma":"مَسْرُور"}],"10":[{"p":1,"ar":"وَأَمَّا","pos":"P","morphemes":[{"ar":"وَ","pos":"REM","prefix":true},{"ar":"أَمَّا","pos":"P"}],"f":{},"lemma":"أَمّا"},{"p":2,"ar":"مَنْ","pos":"COND","morphemes":[{"ar":"مَنْ","pos":"COND"}],"f":{},"lemma":"مَن"},{"p":3,"ar":"أُوتِىَ","pos":"V","morphemes":[{"ar":"أُوتِىَ","pos":"V"}],"f":{"per":3,"gen":"M","num":"S","voice":"PASS","form":4,"asp":"PERF"},"root":"أتي","lemma":"آتَى"},{"p":4,"ar":"كِتَٰبَهُۥ","pos":"N","morphemes":[{"ar":"كِتَٰبَ","pos":"N"},{"ar":"هُۥ","pos":"PRON","suffix":true}],"f":{"gen":"M","cas":"ACC"},"root":"كتب","lemma":"كِتاب"},{"p":5,"ar":"وَرَآءَ","pos":"LOC","morphemes":[{"ar":"وَرَآءَ","pos":"LOC"}],"f":{"cas":"ACC"},"root":"وري","lemma":"وَراء"},{"p":6,"ar":"ظَهْرِهِۦ","pos":"N","morphemes":[{"ar":"ظَهْرِ","pos":"N"},{"ar":"هِۦ","pos":"PRON","suffix":true}],"f":{"gen":"M","cas":"GEN"},"root":"ظهر","lemma":"ظَهْر"}],"11":[{"p":1,"ar":"فَسَوْفَ","pos":"FUT","morphemes":[{"ar":"فَ","pos":"RSLT","prefix":true},{"ar":"سَوْفَ","pos":"FUT"}],"f":{},"lemma":"سَوْف"},{"p":2,"ar":"يَدْعُوا۟","pos":"V","morphemes":[{"ar":"يَدْعُوا۟","pos":"V"}],"f":{"per":3,"gen":"M","num":"S","mood":"IND","form":1,"asp":"IMPF"},"root":"دعو","lemma":"دَعا"},{"p":3,"ar":"ثُبُورًا","pos":"N","morphemes":[{"ar":"ثُبُورًا","pos":"N"}],"f":{"gen":"M","cas":"ACC","state":"INDEF"},"root":"ثبر","lemma":"ثُبُور"}],"12":[{"p":1,"ar":"وَيَصْلَىٰ","pos":"V","morphemes":[{"ar":"وَ","pos":"CONJ","prefix":true},{"ar":"يَصْلَىٰ","pos":"V"}],"f":{"per":3,"gen":"M","num":"S","mood":"IND","form":1,"asp":"IMPF"},"root":"صلي","lemma":"يَصْلَى"},{"p":2,"ar":"سَعِيرًا","pos":"N","morphemes":[{"ar":"سَعِيرًا","pos":"N"}],"f":{"gen":"M","cas":"ACC","state":"INDEF"},"root":"سعر","lemma":"سَعِير"}],"13":[{"p":1,"ar":"إِنَّهُۥ","pos":"P","morphemes":[{"ar":"إِنَّ","pos":"P"},{"ar":"هُۥ","pos":"PRON","suffix":true}],"f":{"cas":"ACC"},"lemma":"إِنّ"},{"p":2,"ar":"كَانَ","pos":"V","morphemes":[{"ar":"كَانَ","pos":"V"}],"f":{"per":3,"gen":"M","num":"S","form":1,"asp":"PERF"},"root":"كون","lemma":"كانَ"},{"p":3,"ar":"فِىٓ","pos":"P","morphemes":[{"ar":"فِىٓ","pos":"P"}],"f":{},"lemma":"فِي"},{"p":4,"ar":"أَهْلِهِۦ","pos":"N","morphemes":[{"ar":"أَهْلِ","pos":"N"},{"ar":"هِۦ","pos":"PRON","suffix":true}],"f":{"gen":"M","cas":"GEN"},"root":"أهل","lemma":"أَهْل"},{"p":5,"ar":"مَسْرُورًا","pos":"N","morphemes":[{"ar":"مَسْرُورًا","pos":"N"}],"f":{"gen":"M","cas":"ACC","state":"INDEF","form":1,"der":"PP"},"root":"سرر","lemma":"مَسْرُور"}],"14":[{"p":1,"ar":"إِنَّهُۥ","pos":"P","morphemes":[{"ar":"إِنَّ","pos":"P"},{"ar":"هُۥ","pos":"PRON","suffix":true}],"f":{"cas":"ACC"},"lemma":"إِنّ"},{"p":2,"ar":"ظَنَّ","pos":"V","morphemes":[{"ar":"ظَنَّ","pos":"V"}],"f":{"per":3,"gen":"M","num":"S","form":1,"asp":"PERF"},"root":"ظنن","lemma":"ظَنَّ"},{"p":3,"ar":"أَن","pos":"SUB","morphemes":[{"ar":"أَن","pos":"SUB"}],"f":{},"lemma":"أَن"},{"p":4,"ar":"لَّن","pos":"NEG","morphemes":[{"ar":"لَّن","pos":"NEG"}],"f":{},"lemma":"لَن"},{"p":5,"ar":"يَحُورَ","pos":"V","morphemes":[{"ar":"يَحُورَ","pos":"V"}],"f":{"per":3,"gen":"M","num":"S","mood":"SUBJ","form":1,"asp":"IMPF"},"root":"حور","lemma":"يَحُورَ"}],"15":[{"p":1,"ar":"بَلَىٰٓ","pos":"ANS","morphemes":[{"ar":"بَلَىٰٓ","pos":"ANS"}],"f":{},"lemma":"بَلَى"},{"p":2,"ar":"إِنَّ","pos":"P","morphemes":[{"ar":"إِنَّ","pos":"P"}],"f":{"cas":"ACC"},"lemma":"إِنّ"},{"p":3,"ar":"رَبَّهُۥ","pos":"N","morphemes":[{"ar":"رَبَّ","pos":"N"},{"ar":"هُۥ","pos":"PRON","suffix":true}],"f":{"gen":"M","cas":"ACC"},"root":"ربب","lemma":"رَبّ"},{"p":4,"ar":"كَانَ","pos":"V","morphemes":[{"ar":"كَانَ","pos":"V"}],"f":{"per":3,"gen":"M","num":"S","form":1,"asp":"PERF"},"root":"كون","lemma":"كانَ"},{"p":5,"ar":"بِهِۦ","pos":"PRON","morphemes":[{"ar":"بِ","pos":"P","prefix":true},{"ar":"هِۦ","pos":"PRON"}],"f":{"per":3,"gen":"M","num":"S"}},{"p":6,"ar":"بَصِيرًا","pos":"N","morphemes":[{"ar":"بَصِيرًا","pos":"N"}],"f":{"gen":"M","num":"S","cas":"ACC","state":"INDEF"},"root":"بصر","lemma":"بَصِير"}],"16":[{"p":1,"ar":"فَلَآ","pos":"NEG","morphemes":[{"ar":"فَ","pos":"REM","prefix":true},{"ar":"لَآ","pos":"NEG"}],"f":{},"lemma":"لا"},{"p":2,"ar":"أُقْسِمُ","pos":"V","morphemes":[{"ar":"أُقْسِمُ","pos":"V"}],"f":{"per":1,"num":"S","mood":"IND","form":4,"asp":"IMPF"},"root":"قسم","lemma":"أَقْسَمُ"},{"p":3,"ar":"بِٱلشَّفَقِ","pos":"N","morphemes":[{"ar":"بِ","pos":"P","prefix":true},{"ar":"ٱل","pos":"DET","prefix":true},{"ar":"شَّفَقِ","pos":"N"}],"f":{"gen":"M","cas":"GEN"},"root":"شفق","lemma":"شَفَق"}],"17":[{"p":1,"ar":"وَٱلَّيْلِ","pos":"N","morphemes":[{"ar":"وَ","pos":"CONJ","prefix":true},{"ar":"ٱلَّ","pos":"DET","prefix":true},{"ar":"يْلِ","pos":"N"}],"f":{"gen":"M","cas":"GEN"},"root":"ليل","lemma":"لَيْل"},{"p":2,"ar":"وَمَا","pos":"REL","morphemes":[{"ar":"وَ","pos":"CONJ","prefix":true},{"ar":"مَا","pos":"REL"}],"f":{},"lemma":"ما"},{"p":3,"ar":"وَسَقَ","pos":"V","morphemes":[{"ar":"وَسَقَ","pos":"V"}],"f":{"per":3,"gen":"M","num":"S","form":1,"asp":"PERF"},"root":"وسق","lemma":"وَسَقَ"}],"18":[{"p":1,"ar":"وَٱلْقَمَرِ","pos":"N","morphemes":[{"ar":"وَ","pos":"CONJ","prefix":true},{"ar":"ٱلْ","pos":"DET","prefix":true},{"ar":"قَمَرِ","pos":"N"}],"f":{"gen":"M","cas":"GEN"},"root":"قمر","lemma":"قَمَر"},{"p":2,"ar":"إِذَا","pos":"T","morphemes":[{"ar":"إِذَا","pos":"T"}],"f":{},"lemma":"إِذا"},{"p":3,"ar":"ٱتَّسَقَ","pos":"V","morphemes":[{"ar":"ٱتَّسَقَ","pos":"V"}],"f":{"per":3,"gen":"M","num":"S","form":8,"asp":"PERF"},"root":"وسق","lemma":"اتَّسَقَ"}],"19":[{"p":1,"ar":"لَتَرْكَبُنَّ","pos":"V","morphemes":[{"ar":"لَ","pos":"EMPH","prefix":true},{"ar":"تَرْكَبُ","pos":"V"},{"ar":"نَّ","pos":"EMPH","suffix":true}],"f":{"per":2,"gen":"M","num":"P","mood":"IND","form":1,"asp":"IMPF"},"root":"ركب","lemma":"رَكِبَ"},{"p":2,"ar":"طَبَقًا","pos":"N","morphemes":[{"ar":"طَبَقًا","pos":"N"}],"f":{"gen":"M","cas":"ACC","state":"INDEF"},"root":"طبق","lemma":"طَبَق"},{"p":3,"ar":"عَن","pos":"P","morphemes":[{"ar":"عَن","pos":"P"}],"f":{},"lemma":"عَن"},{"p":4,"ar":"طَبَقٍ","pos":"N","morphemes":[{"ar":"طَبَقٍ","pos":"N"}],"f":{"gen":"M","cas":"GEN","state":"INDEF"},"root":"طبق","lemma":"طَبَق"}],"20":[{"p":1,"ar":"فَمَا","pos":"INTG","morphemes":[{"ar":"فَ","pos":"REM","prefix":true},{"ar":"مَا","pos":"INTG"}],"f":{},"lemma":"ما"},{"p":2,"ar":"لَهُمْ","pos":"PRON","morphemes":[{"ar":"لَ","pos":"P","prefix":true},{"ar":"هُمْ","pos":"PRON"}],"f":{"per":3,"gen":"M","num":"P"}},{"p":3,"ar":"لَا","pos":"NEG","morphemes":[{"ar":"لَا","pos":"NEG"}],"f":{},"lemma":"لا"},{"p":4,"ar":"يُؤْمِنُونَ","pos":"V","morphemes":[{"ar":"يُؤْمِنُ","pos":"V"},{"ar":"ونَ","pos":"PRON","suffix":true}],"f":{"per":3,"gen":"M","num":"P","mood":"IND","form":4,"asp":"IMPF"},"root":"أمن","lemma":"آمَنَ"}],"21":[{"p":1,"ar":"وَإِذَا","pos":"T","morphemes":[{"ar":"وَ","pos":"CONJ","prefix":true},{"ar":"إِذَا","pos":"T"}],"f":{},"lemma":"إِذا"},{"p":2,"ar":"قُرِئَ","pos":"V","morphemes":[{"ar":"قُرِئَ","pos":"V"}],"f":{"per":3,"gen":"M","num":"S","voice":"PASS","form":1,"asp":"PERF"},"root":"قرأ","lemma":"قَرَأَ"},{"p":3,"ar":"عَلَيْهِمُ","pos":"P","morphemes":[{"ar":"عَلَيْ","pos":"P"},{"ar":"هِمُ","pos":"PRON","suffix":true}],"f":{},"lemma":"عَلَى"},{"p":4,"ar":"ٱلْقُرْءَانُ","pos":"PN","morphemes":[{"ar":"ٱلْ","pos":"DET","prefix":true},{"ar":"قُرْءَانُ","pos":"PN"}],"f":{"gen":"M","cas":"NOM"},"root":"قرأ","lemma":"قُرْءان"},{"p":5,"ar":"لَا","pos":"NEG","morphemes":[{"ar":"لَا","pos":"NEG"}],"f":{},"lemma":"لا"},{"p":6,"ar":"يَسْجُدُونَ","pos":"V","morphemes":[{"ar":"يَسْجُدُ","pos":"V"},{"ar":"ونَ","pos":"PRON","suffix":true}],"f":{"per":3,"gen":"M","num":"P","mood":"IND","form":1,"asp":"IMPF"},"root":"سجد","lemma":"سَجَدَ"}],"22":[{"p":1,"ar":"بَلِ","pos":"P","morphemes":[{"ar":"بَلِ","pos":"P"}],"f":{},"lemma":"بَل"},{"p":2,"ar":"ٱلَّذِينَ","pos":"REL","morphemes":[{"ar":"ٱلَّذِينَ","pos":"REL"}],"f":{"gen":"M","num":"P"},"lemma":"الَّذِي"},{"p":3,"ar":"كَفَرُوا۟","pos":"V","morphemes":[{"ar":"كَفَرُ","pos":"V"},{"ar":"وا۟","pos":"PRON","suffix":true}],"f":{"per":3,"gen":"M","num":"P","form":1,"asp":"PERF"},"root":"كفر","lemma":"كَفَرَ"},{"p":4,"ar":"يُكَذِّبُونَ","pos":"V","morphemes":[{"ar":"يُكَذِّبُ","pos":"V"},{"ar":"ونَ","pos":"PRON","suffix":true}],"f":{"per":3,"gen":"M","num":"P","mood":"IND","form":2,"asp":"IMPF"},"root":"كذب","lemma":"كَذَّبَ"}],"23":[{"p":1,"ar":"وَٱللَّهُ","pos":"PN","morphemes":[{"ar":"وَ","pos":"REM","prefix":true},{"ar":"ٱللَّهُ","pos":"PN"}],"f":{"cas":"NOM"},"root":"أله","lemma":"اللَّه"},{"p":2,"ar":"أَعْلَمُ","pos":"N","morphemes":[{"ar":"أَعْلَمُ","pos":"N"}],"f":{"gen":"M","num":"S","cas":"NOM"},"root":"علم","lemma":"أَعْلَم"},{"p":3,"ar":"بِمَا","pos":"REL","morphemes":[{"ar":"بِ","pos":"P","prefix":true},{"ar":"مَا","pos":"REL"}],"f":{},"lemma":"ما"},{"p":4,"ar":"يُوعُونَ","pos":"V","morphemes":[{"ar":"يُوعُ","pos":"V"},{"ar":"ونَ","pos":"PRON","suffix":true}],"f":{"per":3,"gen":"M","num":"P","mood":"IND","form":4,"asp":"IMPF"},"root":"وعي","lemma":"أَوْعَى"}],"24":[{"p":1,"ar":"فَبَشِّرْهُم","pos":"V","morphemes":[{"ar":"فَ","pos":"P","prefix":true},{"ar":"بَشِّرْ","pos":"V"},{"ar":"هُم","pos":"PRON","suffix":true}],"f":{"per":2,"gen":"M","num":"S","form":2,"asp":"IMPV"},"root":"بشر","lemma":"بُشِّرَ"},{"p":2,"ar":"بِعَذَابٍ","pos":"N","morphemes":[{"ar":"بِ","pos":"P","prefix":true},{"ar":"عَذَابٍ","pos":"N"}],"f":{"gen":"M","cas":"GEN","state":"INDEF"},"root":"عذب","lemma":"عَذاب"},{"p":3,"ar":"أَلِيمٍ","pos":"ADJ","morphemes":[{"ar":"أَلِيمٍ","pos":"ADJ"}],"f":{"gen":"M","num":"S","cas":"GEN","state":"INDEF"},"root":"ألم","lemma":"أَلِيم"}],"25":[{"p":1,"ar":"إِلَّا","pos":"EXP","morphemes":[{"ar":"إِلَّا","pos":"EXP"}],"f":{},"lemma":"إِلّا"},{"p":2,"ar":"ٱلَّذِينَ","pos":"REL","morphemes":[{"ar":"ٱلَّذِينَ","pos":"REL"}],"f":{"gen":"M","num":"P"},"lemma":"الَّذِي"},{"p":3,"ar":"ءَامَنُوا۟","pos":"V","morphemes":[{"ar":"ءَامَنُ","pos":"V"},{"ar":"وا۟","pos":"PRON","suffix":true}],"f":{"per":3,"gen":"M","num":"P","form":4,"asp":"PERF"},"root":"أمن","lemma":"آمَنَ"},{"p":4,"ar":"وَعَمِلُوا۟","pos":"V","morphemes":[{"ar":"وَ","pos":"CONJ","prefix":true},{"ar":"عَمِلُ","pos":"V"},{"ar":"وا۟","pos":"PRON","suffix":true}],"f":{"per":3,"gen":"M","num":"P","form":1,"asp":"PERF"},"root":"عمل","lemma":"عَمِلَ"},{"p":5,"ar":"ٱلصَّٰلِحَٰتِ","pos":"N","morphemes":[{"ar":"ٱل","pos":"DET","prefix":true},{"ar":"صَّٰلِحَٰتِ","pos":"N"}],"f":{"gen":"F","num":"P","cas":"ACC","form":1,"der":"AP"},"root":"صلح","lemma":"صالِحَة"},{"p":6,"ar":"لَهُمْ","pos":"PRON","morphemes":[{"ar":"لَ","pos":"P","prefix":true},{"ar":"هُمْ","pos":"PRON"}],"f":{"per":3,"gen":"M","num":"P"}},{"p":7,"ar":"أَجْرٌ","pos":"N","morphemes":[{"ar":"أَجْرٌ","pos":"N"}],"f":{"gen":"M","cas":"NOM","state":"INDEF"},"root":"أجر","lemma":"أَجْر"},{"p":8,"ar":"غَيْرُ","pos":"ADJ","morphemes":[{"ar":"غَيْرُ","pos":"ADJ"}],"f":{"gen":"M","cas":"NOM"},"root":"غير","lemma":"غَيْر"},{"p":9,"ar":"مَمْنُونٍۭ","pos":"N","morphemes":[{"ar":"مَمْنُونٍۭ","pos":"N"}],"f":{"gen":"M","cas":"GEN","state":"INDEF","form":1,"der":"PP"},"root":"منن","lemma":"مَمْنُون"}]}}